negar/__init__.py
negar/countriesWithTheirCapital.py
negar/negar.py
negar-0.6.0.dist-info/LICENSE
negar-0.6.0.dist-info/METADATA
negar-0.6.0.dist-info/WHEEL
negar-0.6.0.dist-info/top_level.txt
negar-0.6.0.dist-info/RECORD
