Metadata-Version: 2.1
Name: negar
Version: 0.6.0
Summary: call negar in your python source code and error & text log to a file ...
Home-page: https://github.com/sys113/negar
Author: SYS113
Author-email: 051.SYS113@gmail.com
License: UNKNOWN
Keywords: negar,log,error,save
Platform: UNKNOWN
Classifier: Intended Audience :: Developers
Classifier: License :: OSI Approved :: MIT License
Classifier: Natural Language :: English
Classifier: Operating System :: OS Independent
Classifier: Programming Language :: Python :: Implementation
Classifier: Topic :: Software Development :: Libraries :: Python Modules
Requires-Dist: tzlocal
